{"A":{"code_table":{"defs":[{"tag_name":"METHODDEF","sym":110,"flags":68719476736,"tag":4,"type":111,"body":{"is_static":false,"stats":[{"tag_name":"EXEC","expr":{"args":[],"tag_name":"APPLY","tag":26,"meth":{"tag_name":"IDENT","sym":111,"tag":37}},"tag":20},{"tag_name":"EXEC","expr":{"tag_name":"ASSIGN","lhs":{"tag_name":"IDENT","sym":109,"tag":37},"tag":31,"rhs":{"tag_name":"LITERAL","tag":38,"value":1}},"tag":20}],"tag_name":"BLOCK","tag":7}},{"tag_name":"METHODDEF","sym":106,"flags":0,"tag":4,"type":109,"body":{"is_static":false,"stats":[{"init":{"tag_name":"LITERAL","tag":38,"value":0},"tag_name":"VARDEF","sym":112,"flags":0,"tag":5},{"is_void":false,"tag_name":"RETURN","expr":{"tag_name":"PLUS","lhs":{"tag_name":"IDENT","sym":109,"tag":37},"opcode_name":"+","tag":75,"opcode":96,"rhs":{"tag_name":"IDENT","sym":112,"tag":37}},"tag":23}],"tag_name":"BLOCK","tag":7}}],"tag_name":"CLASSDEF","sym":102,"tag":3,"type":100},"symbol_table":[{"owner":101,"flag":8388608,"kind":1,"name":"","kindname":"kindname.package","fullname":"","type":101},{"flag":8388608,"kind":1,"name":"","kindname":"kindname.package","fullname":"","type":102},{"owner":100,"flatname":"A","flag":1143492092887040,"kind":2,"name":"A","kindname":"kindname.class","erasure_field":100,"fullname":"A","type":103,"members_field":[{"sym":106},{"sym":109},{"sym":110}],"sourcefile":"RegularFileObject[/Users/lishijie/workspace/xc5/java_testsuit/SingleFile/SimpleClassWithMethod.java]"},{"owner":104,"flag":8388608,"kind":1,"name":"lang","kindname":"kindname.package","fullname":"java.lang","type":105},{"owner":101,"flag":8388608,"kind":1,"name":"java","kindname":"kindname.package","fullname":"java","type":106},{"owner":103,"flatname":"java.lang.Object","flag":1073741825,"kind":2,"name":"Object","kindname":"kindname.class","erasure_field":107,"fullname":"java.lang.Object","type":104,"sourcefile":"SourceFileObject[Object.java]"},{"owner":102,"flag":0,"kind":16,"name":"foo","kindname":"kindname.method","erasure_field":109,"type":109},{"owner":101,"flag":0,"kind":0,"name":"","kindname":"kindname.nil","type":108},{"owner":107,"flatname":"Method","flag":1073741825,"kind":2,"name":"Method","kindname":"kindname.class","fullname":"Method","type":110},{"owner":102,"flag":262144,"kind":4,"name":"a","kindname":"kindname.variable","erasure_field":5,"type":5},{"owner":102,"flag":69793218560,"kind":16,"name":"\u003cinit\u003e","kindname":"kindname.constructor","erasure_field":111,"type":111},{"owner":105,"flag":1,"kind":16,"name":"\u003cinit\u003e","kindname":"kindname.constructor","erasure_field":112,"type":112},{"owner":106,"flag":2199023517696,"kind":4,"name":"b","kindname":"kindname.variable","erasure_field":5,"type":5}],"type_table":[{"outer_field":108,"tsym":102,"kind":9,"name":"A","kindname":"CLASS"},{"tsym":100,"kind":12,"name":"","kindname":"PACKAGE"},{"tsym":101,"kind":12,"name":"","kindname":"PACKAGE"},{"outer_field":108,"supertype_field":104,"tsym":102,"kind":9,"name":"A","kindname":"CLASS"},{"outer_field":108,"supertype_field":108,"tsym":105,"kind":9,"name":"java.lang.Object","kindname":"CLASS"},{"tsym":103,"kind":12,"name":"java.lang","kindname":"PACKAGE"},{"tsym":104,"kind":12,"name":"java","kindname":"PACKAGE"},{"outer_field":108,"tsym":105,"kind":9,"name":"java.lang.Object","kindname":"CLASS"},{"kind":18,"name":"none","kindname":"NONE"},{"restype":5,"tsym":108,"argtypes":[],"kind":11,"name":"()int","thrown":[],"kindname":"METHOD"},{"outer_field":108,"tsym":108,"kind":9,"name":"Method","kindname":"CLASS"},{"restype":8,"tsym":108,"argtypes":[],"kind":11,"name":"()void","thrown":[],"kindname":"METHOD"},{"restype":8,"tsym":108,"argtypes":[],"kind":11,"name":"()void","thrown":[],"kindname":"METHOD"}]}}